ls_spa/__init__.py
ls_spa/_version.py
ls_spa/ls_spa.py
ls_spa/qmc.py
ls_spa-2.0.0.dist-info/METADATA
ls_spa-2.0.0.dist-info/WHEEL
ls_spa-2.0.0.dist-info/licenses/LICENSE
ls_spa-2.0.0.dist-info/RECORD
