Metadata-Version: 2.4
Name: ls_spa
Version: 2.0.0
Summary: A package for efficient Shapley performance attribution for least-squares problems
Author-email: Logan Bell <20belllemail@gmail.com>, Nikhil Devanathan <nikhil.devanathan@gmail.com>
License-Expression: Apache-2.0
License-File: LICENSE
Requires-Python: >=3.11
Requires-Dist: joblib<2,>=1.4.0
Requires-Dist: numpy<3,>=1.24
Requires-Dist: pandas<3,>=2.0
Requires-Dist: scipy<2,>=1.10
